odoo/addons/connector_search_engine/README.rst
odoo/addons/connector_search_engine/__init__.py
odoo/addons/connector_search_engine/__manifest__.py
odoo/addons/connector_search_engine/components/__init__.py
odoo/addons/connector_search_engine/components/adapter.py
odoo/addons/connector_search_engine/components/core.py
odoo/addons/connector_search_engine/components/deleter.py
odoo/addons/connector_search_engine/components/exporter.py
odoo/addons/connector_search_engine/components/mapper.py
odoo/addons/connector_search_engine/data/ir_cron.xml
odoo/addons/connector_search_engine/i18n/connector_search_engine.pot
odoo/addons/connector_search_engine/migrations/12.0.3.2.0/post-migrate.py
odoo/addons/connector_search_engine/models/__init__.py
odoo/addons/connector_search_engine/models/se_backend.py
odoo/addons/connector_search_engine/models/se_backend_spec_abstract.py
odoo/addons/connector_search_engine/models/se_binding.py
odoo/addons/connector_search_engine/models/se_index.py
odoo/addons/connector_search_engine/readme/CHANGES.rst
odoo/addons/connector_search_engine/readme/CONTRIBUTORS.rst
odoo/addons/connector_search_engine/readme/DESCRIPTION.rst
odoo/addons/connector_search_engine/readme/HISTORY.rst
odoo/addons/connector_search_engine/readme/ROADMAP.rst
odoo/addons/connector_search_engine/security/connector_search_engine_security.xml
odoo/addons/connector_search_engine/security/ir.model.access.csv
odoo/addons/connector_search_engine/static/description/icon.png
odoo/addons/connector_search_engine/static/description/index.html
odoo/addons/connector_search_engine/tests/__init__.py
odoo/addons/connector_search_engine/tests/common.py
odoo/addons/connector_search_engine/tests/models.py
odoo/addons/connector_search_engine/tests/models_mixin.py
odoo/addons/connector_search_engine/tests/test_all.py
odoo/addons/connector_search_engine/tests/fixtures/ir_exports_test.xml
odoo/addons/connector_search_engine/views/se_backend.xml
odoo/addons/connector_search_engine/views/se_menu.xml
odoo12_addon_connector_search_engine-12.0.3.2.1.dist-info/METADATA
odoo12_addon_connector_search_engine-12.0.3.2.1.dist-info/WHEEL
odoo12_addon_connector_search_engine-12.0.3.2.1.dist-info/top_level.txt
odoo12_addon_connector_search_engine-12.0.3.2.1.dist-info/RECORD
