Metadata-Version: 2.1
Name: odoo12-addon-connector-search-engine
Version: 12.0.3.2.1
Summary: Connector Search Engine
Home-page: https://github.com/OCA/search-engine
Author: Akretion,ACSONE SA/NV,Camptocamp,Odoo Community Association (OCA)
Author-email: support@odoo-community.org
License: AGPL-3
Platform: UNKNOWN
Classifier: Programming Language :: Python
Classifier: Framework :: Odoo
Classifier: License :: OSI Approved :: GNU Affero General Public License v3
Requires-Python: >=3.5
Requires-Dist: odoo12-addon-base-jsonify
Requires-Dist: odoo12-addon-connector
Requires-Dist: odoo12-addon-server-environment
Requires-Dist: odoo (<12.1dev,>=12.0a)
Requires-Dist: unidecode
